setup.py
sals_sports_simulator/__init__.py
sals_sports_simulator/sportssim.py
sals_sports_simulator.egg-info/PKG-INFO
sals_sports_simulator.egg-info/SOURCES.txt
sals_sports_simulator.egg-info/dependency_links.txt
sals_sports_simulator.egg-info/not-zip-safe
sals_sports_simulator.egg-info/top_level.txt