Metadata-Version: 2.1
Name: sals-sports-simulator
Version: 1.3
Summary: Simulate the results of a sporting event.
Home-page: UNKNOWN
Author: Sal Cacciatore
Author-email: scacciatore1@gmail.com
License: UNKNOWN
Platform: UNKNOWN
